poly_position_watcher/__init__.py
poly_position_watcher/_version.py
poly_position_watcher/api_worker.py
poly_position_watcher/position_service.py
poly_position_watcher/trade_calculator.py
poly_position_watcher/wss_worker.py
poly_position_watcher/common/__init__.py
poly_position_watcher/common/enums.py
poly_position_watcher/common/logger.py
poly_position_watcher/schema/__init__.py
poly_position_watcher/schema/base.py
poly_position_watcher/schema/common_model.py
poly_position_watcher/schema/position_model.py
poly_position_watcher-0.2.5.dist-info/licenses/LICENSE
poly_position_watcher-0.2.5.dist-info/METADATA
poly_position_watcher-0.2.5.dist-info/WHEEL
poly_position_watcher-0.2.5.dist-info/top_level.txt
poly_position_watcher-0.2.5.dist-info/RECORD
