Metadata-Version: 2.4
Name: poly-position-watcher
Version: 0.2.5
Summary: polymarket proxy wallet redeem
Home-page: https://github.com/tosmart01/polymarket-position-watcher
Author: pinbar
Project-URL: Homepage, https://github.com/tosmart01/polymarket-position-watcher
Requires-Python: >=3.11
License-File: LICENSE
Requires-Dist: loguru>=0.7.3
Requires-Dist: py-clob-client>=0.25.0
Requires-Dist: rich>=14.2.0
Requires-Dist: websocket-client>=1.8.0
Dynamic: author
Dynamic: home-page
Dynamic: license-file
Dynamic: requires-python
